setup.py
quotes_scraper/__init__.py
quotes_scraper/quotes_cacher.py
quotes_scraper/quotes_scraper.py
quotes_scraper.egg-info/PKG-INFO
quotes_scraper.egg-info/SOURCES.txt
quotes_scraper.egg-info/dependency_links.txt
quotes_scraper.egg-info/entry_points.txt
quotes_scraper.egg-info/not-zip-safe
quotes_scraper.egg-info/top_level.txt