Metadata-Version: 1.0
Name: quotes-scraper
Version: 0.2
Summary: Creates quotes from a Goodreads user id.
Home-page: https://github.com/jlitven/Quotes-Scraper
Author: Joshua Litven
Author-email: jlitven@gmail.com
License: MIT
Platform: UNKNOWN
